{
  "flow_type": "data_list",
  "flow_name": "county_riots_alerts",
  "status": "released",
  "rows": [
    {
      "id": "id_1",
      "County": "Uasin Gishu",
      "Riot Probability County": 0.3944,
      "% Change Apr - May County": "3.0%",
      "% Change Mar - Apr County": "-5.0%",
      "Past 2-year Average County": 0.3068,
      "> 2-year Average County": true,
      "Risk-Level County": 5
    },
    {
      "id": "id_2",
      "County": "Taita Taveta",
      "Riot Probability County": 0.1529,
      "% Change Apr - May County": "3.0%",
      "% Change Mar - Apr County": "-1.0%",
      "Past 2-year Average County": 0.1265,
      "> 2-year Average County": true,
      "Risk-Level County": 3.2
    },
    {
      "id": "id_3",
      "County": "Bungoma",
      "Riot Probability County": 0.4255,
      "% Change Apr - May County": "4.0%",
      "% Change Mar - Apr County": "0.0%",
      "Past 2-year Average County": 0.3295,
      "> 2-year Average County": true,
      "Risk-Level County": 5.2
    },
    {
      "id": "id_4",
      "County": "Kirinyaga",
      "Riot Probability County": 0.6564,
      "% Change Apr - May County": "3.0%",
      "% Change Mar - Apr County": "2.0%",
      "Past 2-year Average County": 0.5355,
      "> 2-year Average County": true,
      "Risk-Level County": 6.2
    },
    {
      "id": "id_5",
      "County": "Elgeyo-Marakwet",
      "Riot Probability County": 0.2851,
      "% Change Apr - May County": "4.0%",
      "% Change Mar - Apr County": "-6.0%",
      "Past 2-year Average County": 0.2406,
      "> 2-year Average County": true,
      "Risk-Level County": 4.2
    },
    {
      "id": "id_6",
      "County": "Nyeri",
      "Riot Probability County": 0.4668,
      "% Change Apr - May County": "1.0%",
      "% Change Mar - Apr County": "2.0%",
      "Past 2-year Average County": 0.3503,
      "> 2-year Average County": true,
      "Risk-Level County": 5.5
    },
    {
      "id": "id_7",
      "County": "Kitui",
      "Riot Probability County": 0.3148,
      "% Change Apr - May County": "7.0%",
      "% Change Mar - Apr County": "-4.0%",
      "Past 2-year Average County": 0.2018,
      "> 2-year Average County": true,
      "Risk-Level County": 4.6
    },
    {
      "id": "id_8",
      "County": "Meru",
      "Riot Probability County": 0.406,
      "% Change Apr - May County": "8.0%",
      "% Change Mar - Apr County": "-6.0%",
      "Past 2-year Average County": 0.3131,
      "> 2-year Average County": true,
      "Risk-Level County": 5
    },
    {
      "id": "id_9",
      "County": "Nakuru",
      "Riot Probability County": 0.48,
      "% Change Apr - May County": "-1.0%",
      "% Change Mar - Apr County": "0.0%",
      "Past 2-year Average County": 0.3718,
      "> 2-year Average County": true,
      "Risk-Level County": 5.4
    },
    {
      "id": "id_10",
      "County": "Migori",
      "Riot Probability County": 0.4663,
      "% Change Apr - May County": "1.0%",
      "% Change Mar - Apr County": "-1.0%",
      "Past 2-year Average County": 0.3956,
      "> 2-year Average County": true,
      "Risk-Level County": 5.5
    },
    {
      "id": "id_11",
      "County": "Lamu",
      "Riot Probability County": 0.1404,
      "% Change Apr - May County": "1.0%",
      "% Change Mar - Apr County": "-2.0%",
      "Past 2-year Average County": 0.1694,
      "> 2-year Average County": false,
      "Risk-Level County": 2.5
    },
    {
      "id": "id_12",
      "County": "Nandi",
      "Riot Probability County": 0.3579,
      "% Change Apr - May County": "4.0%",
      "% Change Mar - Apr County": "-1.0%",
      "Past 2-year Average County": 0.2571,
      "> 2-year Average County": true,
      "Risk-Level County": 4.8
    },
    {
      "id": "id_13",
      "County": "Kakamega",
      "Riot Probability County": 0.4801,
      "% Change Apr - May County": "1.0%",
      "% Change Mar - Apr County": "1.0%",
      "Past 2-year Average County": 0.3777,
      "> 2-year Average County": true,
      "Risk-Level County": 5.6
    },
    {
      "id": "id_14",
      "County": "Tana River",
      "Riot Probability County": 0.092,
      "% Change Apr - May County": "1.0%",
      "% Change Mar - Apr County": "-0.0%",
      "Past 2-year Average County": 0.1004,
      "> 2-year Average County": false,
      "Risk-Level County": 2.3
    },
    {
      "id": "id_15",
      "County": "Baringo",
      "Riot Probability County": 0.2826,
      "% Change Apr - May County": "-2.0%",
      "% Change Mar - Apr County": "0.0%",
      "Past 2-year Average County": 0.2416,
      "> 2-year Average County": true,
      "Risk-Level County": 4.3
    },
    {
      "id": "id_16",
      "County": "Busia",
      "Riot Probability County": 0.3989,
      "% Change Apr - May County": "2.0%",
      "% Change Mar - Apr County": "3.0%",
      "Past 2-year Average County": 0.2986,
      "> 2-year Average County": true,
      "Risk-Level County": 5
    },
    {
      "id": "id_17",
      "County": "Kilifi",
      "Riot Probability County": 0.344,
      "% Change Apr - May County": "1.0%",
      "% Change Mar - Apr County": "-4.0%",
      "Past 2-year Average County": 0.2782,
      "> 2-year Average County": true,
      "Risk-Level County": 4.6
    },
    {
      "id": "id_18",
      "County": "Kisii",
      "Riot Probability County": 0.4647,
      "% Change Apr - May County": "1.0%",
      "% Change Mar - Apr County": "1.0%",
      "Past 2-year Average County": 0.4075,
      "> 2-year Average County": true,
      "Risk-Level County": 5.3
    },
    {
      "id": "id_19",
      "County": "Trans Nzoia",
      "Riot Probability County": 0.5111,
      "% Change Apr - May County": "7.0%",
      "% Change Mar - Apr County": "1.0%",
      "Past 2-year Average County": 0.3816,
      "> 2-year Average County": true,
      "Risk-Level County": 5.6
    },
    {
      "id": "id_20",
      "County": "Murang'a",
      "Riot Probability County": 0.3856,
      "% Change Apr - May County": "6.0%",
      "% Change Mar - Apr County": "-7.0%",
      "Past 2-year Average County": 0.3342,
      "> 2-year Average County": true,
      "Risk-Level County": 5
    },
    {
      "id": "id_21",
      "County": "Kwale",
      "Riot Probability County": 0.2186,
      "% Change Apr - May County": "-1.0%",
      "% Change Mar - Apr County": "-5.0%",
      "Past 2-year Average County": 0.2334,
      "> 2-year Average County": false,
      "Risk-Level County": 3.8
    },
    {
      "id": "id_22",
      "County": "Homa Bay",
      "Riot Probability County": 0.4477,
      "% Change Apr - May County": "-5.0%",
      "% Change Mar - Apr County": "6.0%",
      "Past 2-year Average County": 0.3705,
      "> 2-year Average County": true,
      "Risk-Level County": 5.4
    },
    {
      "id": "id_23",
      "County": "Turkana",
      "Riot Probability County": 0.2143,
      "% Change Apr - May County": "6.0%",
      "% Change Mar - Apr County": "-2.0%",
      "Past 2-year Average County": 0.1713,
      "> 2-year Average County": true,
      "Risk-Level County": 3.5
    },
    {
      "id": "id_24",
      "County": "Narok",
      "Riot Probability County": 0.3766,
      "% Change Apr - May County": "-2.0%",
      "% Change Mar - Apr County": "2.0%",
      "Past 2-year Average County": 0.339,
      "> 2-year Average County": true,
      "Risk-Level County": 4.8
    },
    {
      "id": "id_25",
      "County": "Garissa",
      "Riot Probability County": 0.122,
      "% Change Apr - May County": "0.0%",
      "% Change Mar - Apr County": "-1.0%",
      "Past 2-year Average County": 0.1544,
      "> 2-year Average County": false,
      "Risk-Level County": 2.7
    },
    {
      "id": "id_26",
      "County": "Mombasa",
      "Riot Probability County": 0.3422,
      "% Change Apr - May County": "-2.0%",
      "% Change Mar - Apr County": "-6.0%",
      "Past 2-year Average County": 0.3624,
      "> 2-year Average County": false,
      "Risk-Level County": 4.5
    },
    {
      "id": "id_27",
      "County": "Nairobi",
      "Riot Probability County": 0.6825,
      "% Change Apr - May County": "-3.0%",
      "% Change Mar - Apr County": "2.0%",
      "Past 2-year Average County": 0.6393,
      "> 2-year Average County": true,
      "Risk-Level County": 6.5
    },
    {
      "id": "id_28",
      "County": "Kericho",
      "Riot Probability County": 0.4289,
      "% Change Apr - May County": "0.0%",
      "% Change Mar - Apr County": "3.0%",
      "Past 2-year Average County": 0.3357,
      "> 2-year Average County": true,
      "Risk-Level County": 5.3
    },
    {
      "id": "id_29",
      "County": "Mandera",
      "Riot Probability County": 0.0752,
      "% Change Apr - May County": "1.0%",
      "% Change Mar - Apr County": "-2.0%",
      "Past 2-year Average County": 0.0618,
      "> 2-year Average County": true,
      "Risk-Level County": 2.3
    },
    {
      "id": "id_30",
      "County": "Makueni",
      "Riot Probability County": 0.3924,
      "% Change Apr - May County": "-0.0%",
      "% Change Mar - Apr County": "3.0%",
      "Past 2-year Average County": 0.2856,
      "> 2-year Average County": true,
      "Risk-Level County": 5
    },
    {
      "id": "id_31",
      "County": "Laikipia",
      "Riot Probability County": 0.3484,
      "% Change Apr - May County": "-1.0%",
      "% Change Mar - Apr County": "-7.0%",
      "Past 2-year Average County": 0.2934,
      "> 2-year Average County": true,
      "Risk-Level County": 4.7
    },
    {
      "id": "id_32",
      "County": "Machakos",
      "Riot Probability County": 0.5247,
      "% Change Apr - May County": "0.0%",
      "% Change Mar - Apr County": "1.0%",
      "Past 2-year Average County": 0.4218,
      "> 2-year Average County": true,
      "Risk-Level County": 5.8
    },
    {
      "id": "id_33",
      "County": "Embu",
      "Riot Probability County": 0.5664,
      "% Change Apr - May County": "-3.0%",
      "% Change Mar - Apr County": "3.0%",
      "Past 2-year Average County": 0.4308,
      "> 2-year Average County": true,
      "Risk-Level County": 6
    },
    {
      "id": "id_34",
      "County": "West Pokot",
      "Riot Probability County": 0.2726,
      "% Change Apr - May County": "6.0%",
      "% Change Mar - Apr County": "-8.0%",
      "Past 2-year Average County": 0.1982,
      "> 2-year Average County": true,
      "Risk-Level County": 4.2
    },
    {
      "id": "id_35",
      "County": "Marsabit",
      "Riot Probability County": 0.0956,
      "% Change Apr - May County": "2.0%",
      "% Change Mar - Apr County": "-1.0%",
      "Past 2-year Average County": 0.1016,
      "> 2-year Average County": false,
      "Risk-Level County": 2.8
    },
    {
      "id": "id_36",
      "County": "Isiolo",
      "Riot Probability County": 0.3204,
      "% Change Apr - May County": "7.0%",
      "% Change Mar - Apr County": "-4.0%",
      "Past 2-year Average County": 0.2636,
      "> 2-year Average County": true,
      "Risk-Level County": 4
    },
    {
      "id": "id_37",
      "County": "Nyandarua",
      "Riot Probability County": 0.2259,
      "% Change Apr - May County": "-0.0%",
      "% Change Mar - Apr County": "-4.0%",
      "Past 2-year Average County": 0.169,
      "> 2-year Average County": true,
      "Risk-Level County": 3.8
    },
    {
      "id": "id_38",
      "County": "Nyamira",
      "Riot Probability County": 0.4523,
      "% Change Apr - May County": "1.0%",
      "% Change Mar - Apr County": "-2.0%",
      "Past 2-year Average County": 0.3759,
      "> 2-year Average County": true,
      "Risk-Level County": 5.2
    },
    {
      "id": "id_39",
      "County": "Kisumu",
      "Riot Probability County": 0.438,
      "% Change Apr - May County": "-1.0%",
      "% Change Mar - Apr County": "1.0%",
      "Past 2-year Average County": 0.4381,
      "> 2-year Average County": false,
      "Risk-Level County": 5.1
    },
    {
      "id": "id_40",
      "County": "Kiambu",
      "Riot Probability County": 0.5119,
      "% Change Apr - May County": "1.0%",
      "% Change Mar - Apr County": "-2.0%",
      "Past 2-year Average County": 0.4349,
      "> 2-year Average County": true,
      "Risk-Level County": 5.6
    },
    {
      "id": "id_41",
      "County": "Wajir",
      "Riot Probability County": 0.1229,
      "% Change Apr - May County": "1.0%",
      "% Change Mar - Apr County": "-2.0%",
      "Past 2-year Average County": 0.1012,
      "> 2-year Average County": true,
      "Risk-Level County": 2.7
    },
    {
      "id": "id_42",
      "County": "Siaya",
      "Riot Probability County": 0.4983,
      "% Change Apr - May County": "-3.0%",
      "% Change Mar - Apr County": "3.0%",
      "Past 2-year Average County": 0.4703,
      "> 2-year Average County": true,
      "Risk-Level County": 5.5
    },
    {
      "id": "id_43",
      "County": "Tharaka-Nithi",
      "Riot Probability County": 0.3978,
      "% Change Apr - May County": "3.0%",
      "% Change Mar - Apr County": "-3.0%",
      "Past 2-year Average County": 0.3555,
      "> 2-year Average County": true,
      "Risk-Level County": 5.3
    },
    {
      "id": "id_44",
      "County": "Samburu",
      "Riot Probability County": 0.1422,
      "% Change Apr - May County": "-1.0%",
      "% Change Mar - Apr County": "-5.0%",
      "Past 2-year Average County": 0.1039,
      "> 2-year Average County": true,
      "Risk-Level County": 3
    },
    {
      "id": "id_45",
      "County": "Bomet",
      "Riot Probability County": 0.336,
      "% Change Apr - May County": "-3.0%",
      "% Change Mar - Apr County": "4.0%",
      "Past 2-year Average County": 0.2911,
      "> 2-year Average County": true,
      "Risk-Level County": 4.4
    },
    {
      "id": "id_46",
      "County": "Vihiga",
      "Riot Probability County": 0.2406,
      "% Change Apr - May County": "4.0%",
      "% Change Mar - Apr County": "-1.0%",
      "Past 2-year Average County": 0.2159,
      "> 2-year Average County": true,
      "Risk-Level County": 4
    },
    {
      "id": "id_47",
      "County": "Kajiado",
      "Riot Probability County": 0.4796,
      "% Change Apr - May County": "-2.0%",
      "% Change Mar - Apr County": "3.0%",
      "Past 2-year Average County": 0.4568,
      "> 2-year Average County": true,
      "Risk-Level County": 5.4
    }
  ],
  "_xlsxPath": "templates/global/list_view_page.xlsx",
  "_metadata": {
    "Riot Probability County": {
      "type": "number"
    },
    "Past 2-year Average County": {
      "type": "number"
    },
    "> 2-year Average County": {
      "type": "boolean"
    },
    "Risk-Level County": {
      "type": "number"
    }
  }
}